Metadata-Version: 1.0
Name: zptestlib
Version: 1.0.0
Summary: this is a niu bi lib
Home-page: https://github.com/zoupeng/Python_code
Author: zp
Author-email: 610586533@qq.com
License: MIT
Platform: UNKNOWN
